scrub_llm/__init__.py
scrub_llm/cli.py
scrub_llm/placeholders.py
scrub_llm/scrubber.py
scrub_llm/detectors/__init__.py
scrub_llm/detectors/base.py
scrub_llm/detectors/builtin_regex.py
scrub_llm/detectors/entropy.py
scrub_llm/tests/__init__.py
scrub_llm/tests/test_detectors.py
scrub_llm/tests/test_openai_integration.py
scrub_llm/tests/test_placeholders.py
scrub_llm/tests/test_scrubber.py
scrub_llm/transport/__init__.py
scrub_llm/transport/httpx_hook.py
scrub_llm/transport/openai_proxy.py
scrub_llm-0.1.0.dist-info/METADATA
scrub_llm-0.1.0.dist-info/WHEEL
scrub_llm-0.1.0.dist-info/entry_points.txt
scrub_llm-0.1.0.dist-info/licenses/LICENSE
scrub_llm-0.1.0.dist-info/RECORD
