Metadata-Version: 2.4
Name: scrub-llm
Version: 0.1.0
Summary: Drop-in LLM secret scrubber to prevent API key and credential leaks
Project-URL: Homepage, https://github.com/haasonsaas/scrub-llm
Project-URL: Issues, https://github.com/haasonsaas/scrub-llm/issues
Project-URL: Documentation, https://github.com/haasonsaas/scrub-llm#readme
Author-email: Jonathan Haas <jonathan@haas.holdings>
License: MIT
License-File: LICENSE
Keywords: llm,openai,privacy,scrubber,secrets,security
Classifier: Development Status :: 3 - Alpha
Classifier: Intended Audience :: Developers
Classifier: License :: OSI Approved :: MIT License
Classifier: Programming Language :: Python :: 3
Classifier: Programming Language :: Python :: 3.8
Classifier: Programming Language :: Python :: 3.9
Classifier: Programming Language :: Python :: 3.10
Classifier: Programming Language :: Python :: 3.11
Classifier: Programming Language :: Python :: 3.12
Classifier: Topic :: Security
Classifier: Topic :: Software Development :: Libraries :: Python Modules
Requires-Python: >=3.8
Requires-Dist: httpx>=0.24.0
Requires-Dist: openai>=1.0.0
Provides-Extra: dev
Requires-Dist: black>=23.0.0; extra == 'dev'
Requires-Dist: mypy>=1.0.0; extra == 'dev'
Requires-Dist: pytest-asyncio>=0.21.0; extra == 'dev'
Requires-Dist: pytest>=7.0.0; extra == 'dev'
Requires-Dist: respx>=0.20.0; extra == 'dev'
Requires-Dist: ruff>=0.1.0; extra == 'dev'
